MANIFEST.in
README.md
setup.cfg
setup.py
AutoClean/__init__.py
AutoClean/autoclean.py
AutoClean/modules.py
autoclean/modules.py
py_AutoClean.egg-info/PKG-INFO
py_AutoClean.egg-info/SOURCES.txt
py_AutoClean.egg-info/dependency_links.txt
py_AutoClean.egg-info/requires.txt
py_AutoClean.egg-info/top_level.txt