Metadata-Version: 2.1
Name: py-AutoClean
Version: 1.1.3
Summary: AutoClean - Python Package for Automated Preprocessing & Cleaning of Datasets
Home-page: https://github.com/elisemercury/AutoClean
Author: Elise Landman
Author-email: elisejlandman@hotmail.com
License: MIT
Download-URL: https://github.com/elisemercury/AutoClean/archive/refs/tags/v1.1.3.tar.gz
Keywords: automated,cleaning,preprocessing,autoclean
Platform: UNKNOWN
Classifier: Development Status :: 5 - Production/Stable
Classifier: Intended Audience :: Developers
Classifier: Topic :: Software Development :: Build Tools
Classifier: License :: OSI Approved :: MIT License
Classifier: Programming Language :: Python :: 3.7
Classifier: Programming Language :: Python :: 3.8
Classifier: Programming Language :: Python :: 3.9
